cbpy/__init__.py
cricbuzz_py-0.1.2.dist-info/METADATA
cricbuzz_py-0.1.2.dist-info/WHEEL
cricbuzz_py-0.1.2.dist-info/top_level.txt
cricbuzz_py-0.1.2.dist-info/RECORD
