Metadata-Version: 2.1
Name: cricbuzz-py
Version: 0.1.2
Summary: A package to retrive cricket scores
Home-page: https://github.com/aksty/cricbuzz-py
Author: Akshay T
Author-email: sup.aks.apps@gmail.com
License: UNKNOWN
Platform: UNKNOWN
Classifier: Programming Language :: Python :: 3
Classifier: Operating System :: OS Independent
Requires-Python: >=3.6
